tbw/__init__.py
tbw/functionals.py
tbw/wrapper.py
tbw-0.0.3.dist-info/LICENSE
tbw-0.0.3.dist-info/METADATA
tbw-0.0.3.dist-info/WHEEL
tbw-0.0.3.dist-info/top_level.txt
tbw-0.0.3.dist-info/RECORD
