Metadata-Version: 2.1
Name: tbw
Version: 0.0.3
Summary: A wrapper to facilitate tensorboard logging
Home-page: https://ramymounir.com/docs/tbw
Author: Ramy Mounir
Classifier: Programming Language :: Python :: 3
Classifier: License :: Free for non-commercial use
Requires-Python: >=3.11
License-File: LICENSE
Requires-Dist: torch >=2.0.0
Requires-Dist: tensorboard
Requires-Dist: packaging
Requires-Dist: moviepy
